better_einsum/__init__.py
better_einsum/better_einsum.py
better_einsum-1.0.4.dist-info/LICENSE
better_einsum-1.0.4.dist-info/METADATA
better_einsum-1.0.4.dist-info/WHEEL
better_einsum-1.0.4.dist-info/top_level.txt
better_einsum-1.0.4.dist-info/RECORD
